software_collection/__init__.py
software_collection/cli.py
software_collection/collection.py
software_collection-0.0.1.dist-info/METADATA
software_collection-0.0.1.dist-info/WHEEL
software_collection-0.0.1.dist-info/entry_points.txt
software_collection-0.0.1.dist-info/top_level.txt
software_collection-0.0.1.dist-info/RECORD
