Metadata-Version: 2.1
Name: software-collection
Version: 0.0.1
Summary: Manage a collection of git repositories
Author: uuiouuio
Classifier: Programming Language :: Python :: 3
Requires-Python: >=3.9
Requires-Dist: GitPython
